pricewise_hardware/__init__.py
pricewise_hardware/main.py
pricewise_hardware/prompts.py
pricewise_hardware-2025.12.21185315.dist-info/METADATA
pricewise_hardware-2025.12.21185315.dist-info/WHEEL
pricewise_hardware-2025.12.21185315.dist-info/top_level.txt
pricewise_hardware-2025.12.21185315.dist-info/RECORD
