Metadata-Version: 2.4
Name: pricewise-hardware
Version: 2025.12.21185315
Summary: Pricewise-Hardware guides users in buying servers, RAM, flash using LLM7 and llmatch, offering configs, trend insights, and buying tactics.
Author-email: pricewise-hardware <hi@eugene.plus>
License: MIT
Project-URL: Homepage, https://github.com/chigwell/pricewise-hardware
Requires-Python: >=3.9
Requires-Dist: langchain-llm7>=0.0.0
Requires-Dist: llmatch-messages>=0.0.0
Requires-Dist: langchain-core>=0.3.0
